poc_my_common_library/classes/shell.py
poc_my_common_library/main.py
poc_my_common_library-23.7.26.dist-info/METADATA
poc_my_common_library-23.7.26.dist-info/WHEEL
poc_my_common_library-23.7.26.dist-info/entry_points.txt
poc_my_common_library-23.7.26.dist-info/RECORD
